starlette_admin_keycloak/__init__.py
starlette_admin_keycloak/_dto.py
starlette_admin_keycloak/_utils.py
starlette_admin_keycloak/cookies.py
starlette_admin_keycloak/middleware.py
starlette_admin_keycloak/providers.py
starlette_admin_keycloak/py.typed
starlette_admin_keycloak/routes.py
starlette_admin_keycloak-0.3.0.dist-info/METADATA
starlette_admin_keycloak-0.3.0.dist-info/WHEEL
starlette_admin_keycloak-0.3.0.dist-info/top_level.txt
starlette_admin_keycloak-0.3.0.dist-info/RECORD
