Metadata-Version: 2.4
Name: starlette-admin-keycloak
Version: 0.3.0
Summary: Keycloak authentication provider for starlette-admin
Requires-Python: >=3.10
Requires-Dist: python-keycloak>=5.8.0
Requires-Dist: starlette-admin>=0.15.0
